setup.py
pysteam/__init__.py
pysteam/_crc_algorithms.py
pysteam/_shortcut_generator.py
pysteam/_shortcut_parser.py
pysteam/game.py
pysteam/shortcut.py
pysteam/steam.py
pysteam/user.py
pysteam.egg-info/PKG-INFO
pysteam.egg-info/SOURCES.txt
pysteam.egg-info/dependency_links.txt
pysteam.egg-info/not-zip-safe
pysteam.egg-info/top_level.txt