Metadata-Version: 1.0
Name: pysteam
Version: 0.1.3
Summary: Python library to work with Steam
Home-page: http://github.com/scottrice/pysteam
Author: Scott Rice
Author-email: UNKNOWN
License: MIT
Platform: UNKNOWN
